gradio_test3/__init__.py
gradio_test3/test3.py
gradio_test3/test3.pyi
gradio_test3-0.0.2.dist-info/METADATA
gradio_test3-0.0.2.dist-info/WHEEL
gradio_test3-0.0.2.dist-info/RECORD
